swanlab_core/__init__.py
swanlab_core/client.py
swanlab_core/api/__init__.py
swanlab_core/api/v1/__init__.py
swanlab_core/api/v1/core_pb2.py
swanlab_core/api/v1/core_pb2_grpc.py
swanlab_core/bin/core
swanlab_core-0.0.1.dist-info/METADATA
swanlab_core-0.0.1.dist-info/WHEEL
swanlab_core-0.0.1.dist-info/top_level.txt
swanlab_core-0.0.1.dist-info/RECORD
