Metadata-Version: 2.4
Name: swanlab_core
Version: 0.0.1
Summary: SwanLab Core Client with Go Sidecar
Author-email: spigcoder <2240484340@qq.com>
Classifier: Programming Language :: Python :: 3
Classifier: License :: OSI Approved :: MIT License
Classifier: Operating System :: OS Independent
Requires-Python: >=3.8
Requires-Dist: grpcio==1.76.0
Requires-Dist: protobuf>=5
